{
  "file": "/home/andrew/workspace/js/dendro-cli/src/vector/.logs/nginx_error.log",
  "host": "andrew-xps159560",
  "message": "open() \"/spool/logs/nginx-access.log\" failed (2: No such file or directory)",
  "pid": "245775",
  "severity": "emerg",
  "source_type": "file",
  "tid": "245775",
  "timestamp": "2021/04/23 17:28:30 ",
  "type": "nginx-logs"
}
{
  "file": "/home/andrew/workspace/js/dendro-cli/src/vector/.logs/nginx_error.log",
  "host": "andrew-xps159560",
  "message": "open() \"/spool/logs/nginx-access.log\" failed (2: No such file or directory)",
  "pid": "245786",
  "severity": "emerg",
  "source_type": "file",
  "tid": "245786",
  "timestamp": "2021/04/23 17:30:16 ",
  "type": "nginx-logs"
}
{
  "client": "74.82.47.2",
  "connid": "17043",
  "file": "/home/andrew/workspace/js/dendro-cli/src/vector/.logs/nginx_error.log",
  "host": "andrew-xps159560",
  "message": "SSL_do_handshake() failed (SSL: error:141CF06C:SSL routines:tls_parse_ctos_key_share:bad key share) while SSL handshaking",
  "pid": "51144",
  "server": "0.0.0.0:443",
  "severity": "crit",
  "source_type": "file",
  "tid": "51144",
  "timestamp": "2021/04/23 00:29:18 ",
  "type": "nginx-logs"
}